{
  "name":"nine",
  "scale" : 1,
  "alpha" : 0.6,
  "saturation" : 0.5,
  "darken" : false,
  "radius" : 298.7288,
  "paletteMix" : 0,
  "motion" : true,
  "painting" : true,
  "count" : 200,
  "lightness" : 1,
  "useOriginal" : true,
  "length" : 271.1864,
  "hue" : 70,
  "autopaint" : false,
  "shift" : false,
  "palette" : "#fff",
  "background" : "#f1f0e2",
  "thickness" : 100,
  "speed" : 0.5,
  "texture" : 3.915254,
  "viewOriginal" : false,
  "life" : 10,
  "round" : true,
  "angle" : 1,
  "brushImage": "brush09.png",
  "opacity": 0.75
}